top_color_pct/__init__.py
top_color_pct/top_color_pct.py
top_color_pct-0.1.0.dist-info/METADATA
top_color_pct-0.1.0.dist-info/WHEEL
top_color_pct-0.1.0.dist-info/top_level.txt
top_color_pct-0.1.0.dist-info/RECORD
